guzi/__init__.py
guzi/models.py
python-guzi/__init__.py
tests/__init__.py
tests/test_models.py
python_guzi-0.1.3.dist-info/LICENSE
python_guzi-0.1.3.dist-info/METADATA
python_guzi-0.1.3.dist-info/WHEEL
python_guzi-0.1.3.dist-info/top_level.txt
python_guzi-0.1.3.dist-info/RECORD
