Metadata-Version: 2.1
Name: python-guzi
Version: 0.1.3
Summary: A light library to use Guzi in python application
Home-page: https://github.com/GuziEconomy/python-guzi
Author: Guillaume Dubus
Author-email: Guillaume1.dubus@gmail.com
License: UNKNOWN
Platform: UNKNOWN
Classifier: Programming Language :: Python :: 3
Classifier: License :: OSI Approved :: MIT License
Classifier: Operating System :: OS Independent
Requires-Python: >=3.6
Requires-Dist: python-dateutil
